{
	"id": "3901f70c-8c4d-4e17-83c3-bb752ab23a1b",
	"name": "bcar",
	"values": [
		{
			"key": "baseurl",
			"value": "http://localhost:8080",
			"type": "default",
			"enabled": true
		},
		{
			"key": "zoneManagerEmail",
			"value": "zoneManager17@email.com",
			"type": "default",
			"enabled": true
		},
		{
			"key": "partnerEmail",
			"value": "partner17@email.com",
			"type": "any",
			"enabled": true
		},
		{
			"key": "announcerEmail",
			"value": "announce17@email.com",
			"type": "default",
			"enabled": true
		},
		{
			"key": "clientEmail",
			"value": "client17@email.com",
			"type": "default",
			"enabled": true
		},
		{
			"key": "commercialEmail",
			"value": "commercial17@email.com",
			"type": "default",
			"enabled": true
		},
		{
			"key": "JWT_Token",
			"value": "eyJhbGciOiJIUzUxMiJ9.eyJzdWIiOiJhZG1pbiIsImV4cCI6MTc1MDc5MzEzNiwiYXV0aCI6IlJPTEVfQURNSU4gUk9MRV9VU0VSIiwiaWF0IjoxNzUwNzA2NzM2fQ.HFq8jvZVS6fuO9Q4eDomSwEWoXmQ6WOjrCFrhy8vYtZmGfKliTc8LMOPTdj1jcmSZij7tEmgYZaWgOCDMN3_ag",
			"type": "any",
			"enabled": true
		},
		{
			"key": "zoneManagerId",
			"value": 5059,
			"type": "any",
			"enabled": true
		},
		{
			"key": "partnerId",
			"value": 4956,
			"type": "any",
			"enabled": true
		},
		{
			"key": "announcerId",
			"value": 5253,
			"type": "default",
			"enabled": true
		},
		{
			"key": "commercialId",
			"value": 5303,
			"type": "default",
			"enabled": true
		},
		{
			"key": "creatorId",
			"value": "1",
			"type": "default",
			"enabled": true
		},
		{
			"key": "JWT_Token_ZoneManager",
			"value": "eyJhbGciOiJIUzUxMiJ9.eyJzdWIiOiJ6b25lbWFuYWdlcjFAZW1haWwuY29tIiwiZXhwIjoxNzUwNzkzMTI0LCJhdXRoIjoiUk9MRV9aT05FX01BTkFHRVIiLCJpYXQiOjE3NTA3MDY3MjR9.ubN1gwMAnvO31lxwMjysQUQZHYPa3NcExdqvFFvOK3xB4JnN5ySUWeTstKV0ZjaqIFULUxhHmLbgW5DbFC3BGw",
			"type": "any",
			"enabled": true
		},
		{
			"key": "clientId",
			"value": 5354,
			"type": "default",
			"enabled": true
		},
		{
			"key": "offerId",
			"value": 5405,
			"type": "any",
			"enabled": true
		},
		{
			"key": "discountId",
			"value": 5108,
			"type": "default",
			"enabled": true
		},
		{
			"key": "packId",
			"value": 5160,
			"type": "default",
			"enabled": true
		},
		{
			"key": "publicationId",
			"value": 5455,
			"type": "any",
			"enabled": true
		}
	],
	"_postman_variable_scope": "environment",
	"_postman_exported_at": "2025-06-23T19:28:04.383Z",
	"_postman_exported_using": "Postman/11.50.6"
}